fsq_wrapper/__init__.py
fsq_wrapper/api_functions.py
fsq_wrapper/api_helpers.py
fsq_wrapper/helpers.py
fsq_wrapper/input_helpers.py
fsq_wrapper-0.0.5.dist-info/DESCRIPTION.rst
fsq_wrapper-0.0.5.dist-info/METADATA
fsq_wrapper-0.0.5.dist-info/RECORD
fsq_wrapper-0.0.5.dist-info/WHEEL
fsq_wrapper-0.0.5.dist-info/entry_points.txt
fsq_wrapper-0.0.5.dist-info/metadata.json
fsq_wrapper-0.0.5.dist-info/top_level.txt
